[
  {
    "name": "Dagger",
    "damage": "Str+d4",
    "weight": 1,
    "cost": 25,
    "description": "N/A",
    "range": 0,
    "armor_piercing": 0,
    "fire_rate": 0,
    "ammo": "-"
  },
  {
    "name": "Great Sword",
    "damage": "Str+d10",
    "weight": 12,
    "cost": 400,
    "description": "Parry –1, 2 hands",
    "range": 0,
    "armor_piercing": 0,
    "fire_rate": 0,
    "ammo": "-"
  },
  {
    "name": "Flail",
    "damage": "Str+d6",
    "weight": 8,
    "cost": 200,
    "description": "Ignores Shield Parry and Cover bonus",
    "range": 0,
    "armor_piercing": 0,
    "fire_rate": 0,
    "ammo": "-"
  },
  {
    "name": "Katana",
    "damage": "Str+d6+2",
    "weight": 6,
    "cost": 1000,
    "description": "AP2",
    "range": 0,
    "armor_piercing": 0,
    "fire_rate": 0,
    "ammo": "-"
  },
  {
    "name": "Long Sword",
    "damage": "Str+d8",
    "weight": 8,
    "cost": 300,
    "description": "Includes scimitars",
    "range": 0,
    "armor_piercing": 0,
    "fire_rate": 0,
    "ammo": "-"
  },
  {
    "name": "Rapier",
    "damage": "Str+d4",
    "weight": 3,
    "cost": 150,
    "description": "Parry +1",
    "range": 0,
    "armor_piercing": 0,
    "fire_rate": 0,
    "ammo": "-"
  },
  {
    "name": "Short Sword",
    "damage": "Str+d6",
    "weight": 4,
    "cost": 200,
    "description": "Includes cavalry sabers",
    "range": 0,
    "armor_piercing": 0,
    "fire_rate": 0,
    "ammo": "-"
  },
  {
    "name": "Axe",
    "damage": "Str+d6",
    "weight": 2,
    "cost": 200,
    "description": "N/A",
    "range": 0,
    "armor_piercing": 0,
    "fire_rate": 0,
    "ammo": "-"
  },
  {
    "name": "Battle Axe",
    "damage": "Str+d8",
    "weight": 10,
    "cost": 300,
    "description": "N/A",
    "range": 0,
    "armor_piercing": 0,
    "fire_rate": 0,
    "ammo": "-"
  },
  {
    "name": "Great Axe",
    "damage": "Str+d10",
    "weight": 15,
    "cost": 500,
    "description": "AP 1, Parry –1, 2 hands",
    "range": 0,
    "armor_piercing": 0,
    "fire_rate": 0,
    "ammo": "-"
  },
  {
    "name": "Maul",
    "damage": "Str+d8",
    "weight": 20,
    "cost": 400,
    "description": "AP 2 vs. rigid armor, Parry –1, 2 hands",
    "range": 0,
    "armor_piercing": 0,
    "fire_rate": 0,
    "ammo": "-"
  },
  {
    "name": "Warhammer",
    "damage": "Str+d6",
    "weight": 8,
    "cost": 250,
    "description": "AP 1 vs. rigid armor (plate mail)",
    "range": 0,
    "armor_piercing": 0,
    "fire_rate": 0,
    "ammo": "-"
  },
  {
    "name": "Halberd",
    "damage": "Str+d8",
    "weight": 15,
    "cost": 250,
    "description": "Reach 1, 2 hands",
    "range": 0,
    "armor_piercing": 0,
    "fire_rate": 0,
    "ammo": "-"
  },
  {
    "name": "Lance",
    "damage": "Str+d8",
    "weight": 10,
    "cost": 300,
    "description": "AP 2 when charging, Reach 2, only usable in mounted combat",
    "range": 0,
    "armor_piercing": 0,
    "fire_rate": 0,
    "ammo": "-"
  },
  {
    "name": "Pike",
    "damage": "Str+d8",
    "weight": 25,
    "cost": 400,
    "description": "Reach 2, requires 2 hands",
    "range": 0,
    "armor_piercing": 0,
    "fire_rate": 0,
    "ammo": "-"
  },
  {
    "name": "Staff",
    "damage": "Str+d4",
    "weight": 8,
    "cost": 10,
    "description": "Parry +1, Reach 1, 2 hands",
    "range": 0,
    "armor_piercing": 0,
    "fire_rate": 0,
    "ammo": "-"
  },
  {
    "name": "Spear",
    "damage": "Str+d6",
    "weight": 5,
    "cost": 100,
    "description": "Parry +1, Reach 1, 2 hands",
    "range": 0,
    "armor_piercing": 0,
    "fire_rate": 0,
    "ammo": "-"
  },
  {
    "name": "Bangstick",
    "damage": "3d6",
    "weight": 2,
    "cost": 5,
    "description": "Basically a shotgun shell on a stick used in melee; must be reloaded with a fresh shell. (1 action)",
    "range": 0,
    "armor_piercing": 0,
    "fire_rate": 0,
    "ammo": "-"
  },
  {
    "name": "Bayonet",
    "damage": "Str+d4",
    "weight": 1,
    "cost": 25,
    "description": "A bayonet affixed to a rifle increases the damage to Str+d6, Parry +1, Reach 1, 2 hands",
    "range": 0,
    "armor_piercing": 0,
    "fire_rate": 0,
    "ammo": "-"
  },
  {
    "name": "Billy Club/Baton",
    "damage": "Str+d4",
    "weight": 1,
    "cost": 10,
    "description": "Carried by most law-enforcement officials",
    "range": 0,
    "armor_piercing": 0,
    "fire_rate": 0,
    "ammo": "-"
  },
  {
    "name": "Brass Knuckles",
    "damage": "Str+d4",
    "weight": 1,
    "cost": 20,
    "description": "A hero wearing brass knuckles is considered to be an Unarmed Attacker",
    "range": 0,
    "armor_piercing": 0,
    "fire_rate": 0,
    "ammo": "-"
  },
  {
    "name": "Chainsaw",
    "damage": "2d6+4",
    "weight": 20,
    "cost": 200,
    "description": "A natural 1 on the Fighting die (regardless of the Wild Die) hits the user instead",
    "range": 0,
    "armor_piercing": 0,
    "fire_rate": 0,
    "ammo": "-"
  },
  {
    "name": "Switchblade",
    "damage": "Str+d4",
    "weight": 1,
    "cost": 10,
    "description": "–2 to be Noticed if hidden",
    "range": 0,
    "armor_piercing": 0,
    "fire_rate": 0,
    "ammo": "-"
  },
  {
    "name": "Survival Knife",
    "damage": "Str+d4",
    "weight": 3,
    "cost": 50,
    "description": "Contains supplies that add +1 to Survival rolls",
    "range": 0,
    "armor_piercing": 0,
    "fire_rate": 0,
    "ammo": "-"
  },
  {
    "name": "Chain/Vibro Blade",
    "damage": "+1d6",
    "weight": 2,
    "cost": 500,
    "description": "Vibrates loudly. AP+2",
    "range": 0,
    "armor_piercing": 0,
    "fire_rate": 0,
    "ammo": "-"
  },
  {
    "name": "Energy Weapon",
    "damage": "Die Increase",
    "weight": 1,
    "cost": 500,
    "description": "Blade of pure energy. Increases damage by 1 die type. +4 AP. No minimum Str. Heavy Weapon",
    "range": 0,
    "armor_piercing": 0,
    "fire_rate": 0,
    "ammo": "-"
  },
  {
    "name": "Molecular Blade",
    "damage": "+2",
    "weight": 1,
    "cost": 500,
    "description": "Extremely thin edge. +1/2 the weapon's die type in AP.",
    "range": 0,
    "armor_piercing": 0,
    "fire_rate": 0,
    "ammo": "-"
  },
  {
    "name": "Power Weapon",
    "damage": "+1d6",
    "weight": 1,
    "cost": 500,
    "description": "Variable burst of energy released on impact. On a raise, the extra die is a d10 instead of a d6.",
    "range": 0,
    "armor_piercing": 0,
    "fire_rate": 0,
    "ammo": "-"
  },
  {
    "name": "Stun Charge",
    "damage": "-",
    "weight": 1,
    "cost": 500,
    "description": "Blunt weapons only. Victim must make Vigor roll or fall prone/incapacitated. Vigor roll each turn to revive. Success=revived but shaken. Raise=not shaken.",
    "range": 0,
    "armor_piercing": 0,
    "fire_rate": 0,
    "ammo": "-"
  },
  {
    "name": "Axe, Throwing",
    "damage": "Str+d6",
    "weight": 2,
    "cost": 75,
    "description": "-",
    "range": 12,
    "armor_piercing": 0,
    "fire_rate": 1,
    "ammo": "-"
  },
  {
    "name": "Bow",
    "damage": "2d6",
    "weight": 3,
    "cost": 250,
    "description": "1 Action to reload",
    "range": 48,
    "armor_piercing": 2,
    "fire_rate": 1,
    "ammo": "-"
  },
  {
    "name": "Crossbow",
    "damage": "2d6",
    "weight": 10,
    "cost": 500,
    "description": "-",
    "range": 60,
    "armor_piercing": 0,
    "fire_rate": 1,
    "ammo": "-"
  },
  {
    "name": "English Longbow",
    "damage": "2d6",
    "weight": 5,
    "cost": 200,
    "description": "-",
    "range": 60,
    "armor_piercing": 0,
    "fire_rate": 1,
    "ammo": "-"
  },
  {
    "name": "Knife/Dagger",
    "damage": "Str+d4",
    "weight": 1,
    "cost": 25,
    "description": "-",
    "range": 12,
    "armor_piercing": 0,
    "fire_rate": 1,
    "ammo": "-"
  },
  {
    "name": "Sling",
    "damage": "Str+d4",
    "weight": 1,
    "cost": 10,
    "description": "-",
    "range": 16,
    "armor_piercing": 0,
    "fire_rate": 1,
    "ammo": "-"
  },
  {
    "name": "Spear",
    "damage": "Str+d6",
    "weight": 5,
    "cost": 100,
    "description": "-",
    "range": 12,
    "armor_piercing": 0,
    "fire_rate": 1,
    "ammo": "-"
  },
  {
    "name": "Brown Bess",
    "damage": "2d8",
    "weight": 15,
    "cost": 300,
    "description": "2 Actions to reload",
    "range": 40,
    "armor_piercing": 0,
    "fire_rate": 1,
    "ammo": ".75"
  },
  {
    "name": "Blunderbuss",
    "damage": "1-3d6",
    "weight": 12,
    "cost": 300,
    "description": "2 Actions to reload",
    "range": 40,
    "armor_piercing": 0,
    "fire_rate": 1,
    "ammo": "8G"
  },
  {
    "name": "Flintlock Pistol",
    "damage": "2d6+1",
    "weight": 3,
    "cost": 150,
    "description": "2 Actions to reload",
    "range": 20,
    "armor_piercing": 0,
    "fire_rate": 1,
    "ammo": ".60"
  },
  {
    "name": "Kentucky Rifle",
    "damage": "2d8",
    "weight": 8,
    "cost": 300,
    "description": "3 Actions to reload",
    "range": 60,
    "armor_piercing": 2,
    "fire_rate": 1,
    "ammo": ".45"
  },
  {
    "name": "Springfield",
    "damage": "2d8",
    "weight": 11,
    "cost": 250,
    "description": "2 Actions to reload",
    "range": 60,
    "armor_piercing": 0,
    "fire_rate": 1,
    "ammo": ".52"
  },
  {
    "name": "Derringer",
    "damage": "2d6+1",
    "weight": 2,
    "cost": 150,
    "description": "-",
    "range": 20,
    "armor_piercing": 1,
    "fire_rate": 1,
    "ammo": ".44"
  },
  {
    "name": "Cold Dragoon",
    "damage": "2d6+1",
    "weight": 4,
    "cost": 200,
    "description": "Revolver",
    "range": 48,
    "armor_piercing": 0,
    "fire_rate": 1,
    "ammo": ".44"
  },
  {
    "name": "Colt 1911",
    "damage": "2d6+1",
    "weight": 4,
    "cost": 200,
    "description": "Semi-Auto",
    "range": 48,
    "armor_piercing": 1,
    "fire_rate": 1,
    "ammo": ".45"
  },
  {
    "name": "S&W",
    "damage": "2d6+1",
    "weight": 5,
    "cost": 250,
    "description": "Revolver",
    "range": 48,
    "armor_piercing": 1,
    "fire_rate": 1,
    "ammo": ".44"
  },
  {
    "name": "Desert Eagle",
    "damage": "2d8",
    "weight": 8,
    "cost": 300,
    "description": "Semi-Auto",
    "range": 60,
    "armor_piercing": 2,
    "fire_rate": 1,
    "ammo": ".50"
  },
  {
    "name": "Glock",
    "damage": "2d6",
    "weight": 3,
    "cost": 200,
    "description": "Semi-Auto",
    "range": 48,
    "armor_piercing": 1,
    "fire_rate": 1,
    "ammo": "9mm"
  },
  {
    "name": "Peacemaker",
    "damage": "2d6+1",
    "weight": 3,
    "cost": 200,
    "description": "Revolver",
    "range": 48,
    "armor_piercing": 1,
    "fire_rate": 1,
    "ammo": ".45"
  },
  {
    "name": "Ruger",
    "damage": "2d6-1",
    "weight": 2,
    "cost": 100,
    "description": "Semi-Auto",
    "range": 40,
    "armor_piercing": 0,
    "fire_rate": 1,
    "ammo": ".22"
  },
  {
    "name": "S&W",
    "damage": "2d6+1",
    "weight": 4,
    "cost": 250,
    "description": "Revolver",
    "range": 48,
    "armor_piercing": 1,
    "fire_rate": 1,
    "ammo": ".357"
  },
  {
    "name": "H&K MP5",
    "damage": "2d6",
    "weight": 10,
    "cost": 300,
    "description": "Auto",
    "range": 48,
    "armor_piercing": 1,
    "fire_rate": 3,
    "ammo": "9mm"
  },
  {
    "name": "MP40",
    "damage": "2d6",
    "weight": 11,
    "cost": 300,
    "description": "Auto",
    "range": 48,
    "armor_piercing": 1,
    "fire_rate": 3,
    "ammo": "9mm"
  },
  {
    "name": "Tommy Gun",
    "damage": "2d6+1",
    "weight": 13,
    "cost": 350,
    "description": "Auto",
    "range": 48,
    "armor_piercing": 1,
    "fire_rate": 3,
    "ammo": ".45"
  },
  {
    "name": "Uzi",
    "damage": "2d6",
    "weight": 9,
    "cost": 300,
    "description": "Auto",
    "range": 48,
    "armor_piercing": 1,
    "fire_rate": 3,
    "ammo": "9mm"
  },
  {
    "name": "Double-Barrel",
    "damage": "1-3d6",
    "weight": 11,
    "cost": 150,
    "description": "+2 Shoot 3d6/2d6/1d6",
    "range": 48,
    "armor_piercing": 0,
    "fire_rate": 1,
    "ammo": "12g"
  },
  {
    "name": "Pump Action",
    "damage": "1-3d6",
    "weight": 8,
    "cost": 150,
    "description": "As Double Barrel",
    "range": 48,
    "armor_piercing": 0,
    "fire_rate": 1,
    "ammo": "12g"
  },
  {
    "name": "Sawed-Off DB",
    "damage": "1-3d6",
    "weight": 6,
    "cost": 150,
    "description": "As Double Barrel",
    "range": 20,
    "armor_piercing": 0,
    "fire_rate": 2,
    "ammo": "12g"
  },
  {
    "name": "Streetsweeper",
    "damage": "1-3d6",
    "weight": 10,
    "cost": 450,
    "description": "As Double Barrel",
    "range": 48,
    "armor_piercing": 0,
    "fire_rate": 1,
    "ammo": "12g"
  },
  {
    "name": "Barrett",
    "damage": "2d10",
    "weight": 35,
    "cost": 750,
    "description": "Snapfire, Heavy Weapon",
    "range": 200,
    "armor_piercing": 4,
    "fire_rate": 1,
    "ammo": ".50"
  },
  {
    "name": "M1",
    "damage": "2d8",
    "weight": 10,
    "cost": 300,
    "description": "Semi-Auto",
    "range": 96,
    "armor_piercing": 2,
    "fire_rate": 1,
    "ammo": ".30"
  },
  {
    "name": "Kar98",
    "damage": "2d8",
    "weight": 9,
    "cost": 300,
    "description": "-",
    "range": 96,
    "armor_piercing": 2,
    "fire_rate": 1,
    "ammo": "7.92"
  },
  {
    "name": "Sharps Big 50",
    "damage": "2d10",
    "weight": 11,
    "cost": 400,
    "description": "Snapfire Penalty",
    "range": 120,
    "armor_piercing": 2,
    "fire_rate": 1,
    "ammo": ".50"
  },
  {
    "name": "Spencer Carbine",
    "damage": "2d8",
    "weight": 8,
    "cost": 250,
    "description": "-",
    "range": 80,
    "armor_piercing": 2,
    "fire_rate": 1,
    "ammo": ".52"
  },
  {
    "name": "Winchester '76",
    "damage": "2d8",
    "weight": 10,
    "cost": 300,
    "description": "-",
    "range": 96,
    "armor_piercing": 2,
    "fire_rate": 1,
    "ammo": ".45-.47"
  },
  {
    "name": "AK47",
    "damage": "2d8+1",
    "weight": 10,
    "cost": 450,
    "description": "Auto",
    "range": 96,
    "armor_piercing": 2,
    "fire_rate": 3,
    "ammo": "7.62"
  },
  {
    "name": "H&K G3",
    "damage": "2d8",
    "weight": 10,
    "cost": 400,
    "description": "Auto",
    "range": 96,
    "armor_piercing": 2,
    "fire_rate": 3,
    "ammo": ".308"
  },
  {
    "name": "M-16",
    "damage": "2d8",
    "weight": 8,
    "cost": 400,
    "description": "Auto, 3RB",
    "range": 96,
    "armor_piercing": 2,
    "fire_rate": 3,
    "ammo": "5.56"
  },
  {
    "name": "Steyr AUG",
    "damage": "2d8",
    "weight": 8,
    "cost": 400,
    "description": "Auto, 3RB",
    "range": 96,
    "armor_piercing": 2,
    "fire_rate": 3,
    "ammo": "5.56"
  },
  {
    "name": "Gatling",
    "damage": "2d8",
    "weight": 40,
    "cost": 500,
    "description": "May not move",
    "range": 96,
    "armor_piercing": 2,
    "fire_rate": 3,
    "ammo": ".45"
  },
  {
    "name": "M2 Browning",
    "damage": "2d10",
    "weight": 84,
    "cost": 1000,
    "description": "May not move, HW",
    "range": 96,
    "armor_piercing": 4,
    "fire_rate": 3,
    "ammo": ".50"
  },
  {
    "name": "M1919",
    "damage": "2d8",
    "weight": 32,
    "cost": 750,
    "description": "May not move",
    "range": 96,
    "armor_piercing": 2,
    "fire_rate": 3,
    "ammo": ".30"
  },
  {
    "name": "M60",
    "damage": "2d8+1",
    "weight": 33,
    "cost": 1000,
    "description": "Snapfire",
    "range": 120,
    "armor_piercing": 2,
    "fire_rate": 3,
    "ammo": "7.62"
  },
  {
    "name": "7.7 MG",
    "damage": "2d8",
    "weight": 30,
    "cost": 1000,
    "description": "Auto, Snapfire",
    "range": 120,
    "armor_piercing": 2,
    "fire_rate": 3,
    "ammo": "7.92"
  },
  {
    "name": "MG34",
    "damage": "2d8+1",
    "weight": 26,
    "cost": 500,
    "description": "Snapfire",
    "range": 120,
    "armor_piercing": 2,
    "fire_rate": 3,
    "ammo": "7.92"
  },
  {
    "name": "MG42",
    "damage": "2d8+1",
    "weight": 26,
    "cost": 500,
    "description": "Snapfire",
    "range": 120,
    "armor_piercing": 2,
    "fire_rate": 4,
    "ammo": "7.92"
  },
  {
    "name": "SAW",
    "damage": "2d8",
    "weight": 20,
    "cost": 750,
    "description": "Snapfire",
    "range": 120,
    "armor_piercing": 2,
    "fire_rate": 4,
    "ammo": "5.56"
  },
  {
    "name": "Besa MG",
    "damage": "2d8",
    "weight": 54,
    "cost": 1000,
    "description": "Auto, May not move",
    "range": 160,
    "armor_piercing": 2,
    "fire_rate": 3,
    "ammo": "7.92"
  },
  {
    "name": "DTMG",
    "damage": "2d8+1",
    "weight": 26,
    "cost": 1000,
    "description": "Auto, May not move",
    "range": 120,
    "armor_piercing": 2,
    "fire_rate": 3,
    "ammo": "7.62"
  },
  {
    "name": "14.5mm MG",
    "damage": "3d6",
    "weight": 30,
    "cost": 5000,
    "description": "Auto, May not move",
    "range": 200,
    "armor_piercing": 2,
    "fire_rate": 3,
    "ammo": "14.5mm"
  },
  {
    "name": "Assault Rifle",
    "damage": "2d8+1",
    "weight": 11,
    "cost": 1500,
    "description": "SA, 3RB",
    "range": 96,
    "armor_piercing": 3,
    "fire_rate": 3,
    "ammo": "Special"
  },
  {
    "name": "Blaster Pistol",
    "damage": "2d6+2",
    "weight": 1,
    "cost": 300,
    "description": "SA",
    "range": 48,
    "armor_piercing": 2,
    "fire_rate": 1,
    "ammo": "Particle Pack"
  },
  {
    "name": "Blaster Rifle",
    "damage": "2d8+2",
    "weight": 5,
    "cost": 500,
    "description": "SA",
    "range": 96,
    "armor_piercing": 2,
    "fire_rate": 1,
    "ammo": "Particle Pack"
  },
  {
    "name": "Blaster SMG",
    "damage": "2d6+2",
    "weight": 1,
    "cost": 300,
    "description": "SA",
    "range": 48,
    "armor_piercing": 2,
    "fire_rate": 3,
    "ammo": "Particle Pack"
  },
  {
    "name": "Disintigrating Pistol",
    "damage": "3d10",
    "weight": 5,
    "cost": 3000,
    "description": "Ultra Tech. HW.",
    "range": 12,
    "armor_piercing": 0,
    "fire_rate": 1,
    "ammo": "Special"
  },
  {
    "name": "Disintigrating Rifle",
    "damage": "3d10",
    "weight": 12,
    "cost": 10000,
    "description": "Ultra Tech. HW.",
    "range": 20,
    "armor_piercing": 0,
    "fire_rate": 1,
    "ammo": "Special"
  },
  {
    "name": "Flak Gun",
    "damage": "3d6+2",
    "weight": 15,
    "cost": 500,
    "description": "LBT. Full-Body armor counts double. Ammo: $40 , 1lb",
    "range": 48,
    "armor_piercing": 0,
    "fire_rate": 1,
    "ammo": "Special"
  },
  {
    "name": "Flechette Gun",
    "damage": "2d4+1",
    "weight": 4,
    "cost": 600,
    "description": "Notes",
    "range": 48,
    "armor_piercing": 0,
    "fire_rate": 3,
    "ammo": "Special"
  },
  {
    "name": "Gatling Blaster",
    "damage": "2d8+4",
    "weight": 12,
    "cost": 800,
    "description": "Notes",
    "range": 48,
    "armor_piercing": 2,
    "fire_rate": 4,
    "ammo": "Particle Pack"
  },
  {
    "name": "Gatling Laser",
    "damage": "3d6+4",
    "weight": 20,
    "cost": 1000,
    "description": "No recoil penalty. Energy drum: $50, 4 lb.",
    "range": 200,
    "armor_piercing": 2,
    "fire_rate": 4,
    "ammo": "Special"
  },
  {
    "name": "Grenade",
    "damage": "By Type",
    "weight": 0,
    "cost": 50,
    "description": "See Ammo For Details.",
    "range": 20,
    "armor_piercing": 0,
    "fire_rate": 1,
    "ammo": "Special"
  },
  {
    "name": "Grenade Launcher",
    "damage": "By Type",
    "weight": 8,
    "cost": 700,
    "description": "See Ammo For Details.",
    "range": 96,
    "armor_piercing": 0,
    "fire_rate": 1,
    "ammo": "Special"
  },
  {
    "name": "Gyroget Pistol",
    "damage": "By Type",
    "weight": 3,
    "cost": 400,
    "description": "HW,",
    "range": 48,
    "armor_piercing": 0,
    "fire_rate": 1,
    "ammo": "Special"
  },
  {
    "name": "Gyroget Rifle",
    "damage": "By Type",
    "weight": 10,
    "cost": 600,
    "description": "HW.",
    "range": 96,
    "armor_piercing": 0,
    "fire_rate": 1,
    "ammo": "Special"
  },
  {
    "name": "Hand Flamer",
    "damage": "2d12",
    "weight": 5,
    "cost": 500,
    "description": "HW.",
    "range": 10,
    "armor_piercing": 0,
    "fire_rate": 1,
    "ammo": "Special"
  },
  {
    "name": "Heavy Flamer",
    "damage": "3d12",
    "weight": 30,
    "cost": 1000,
    "description": "HW. Cone or MBT",
    "range": 10,
    "armor_piercing": 0,
    "fire_rate": 1,
    "ammo": "Special"
  },
  {
    "name": "Hunting Rifle",
    "damage": "2d8+1",
    "weight": 6,
    "cost": 600,
    "description": "Snapfire",
    "range": 96,
    "armor_piercing": 3,
    "fire_rate": 1,
    "ammo": "Special"
  },
  {
    "name": "Laser Pistol",
    "damage": "2d6",
    "weight": 2,
    "cost": 250,
    "description": "SA",
    "range": 60,
    "armor_piercing": 2,
    "fire_rate": 1,
    "ammo": "Special"
  },
  {
    "name": "Laser Rifle",
    "damage": "3d6",
    "weight": 8,
    "cost": 700,
    "description": "SA. No recoil penalty",
    "range": 120,
    "armor_piercing": 2,
    "fire_rate": 3,
    "ammo": "Special"
  },
  {
    "name": "Laser SMG",
    "damage": "2d6",
    "weight": 4,
    "cost": 500,
    "description": "SA. No recoil penalty",
    "range": 60,
    "armor_piercing": 2,
    "fire_rate": 4,
    "ammo": "Special"
  },
  {
    "name": "Machine Gun, Heavy",
    "damage": "2d10",
    "weight": 65,
    "cost": 700,
    "description": "HW. Typically mounted",
    "range": 200,
    "armor_piercing": 4,
    "fire_rate": 3,
    "ammo": "Special"
  },
  {
    "name": "Machine Gun, Light",
    "damage": "2d8",
    "weight": 20,
    "cost": 700,
    "description": "Notes",
    "range": 120,
    "armor_piercing": 2,
    "fire_rate": 4,
    "ammo": "Special"
  },
  {
    "name": "Minigun",
    "damage": "2d8+4",
    "weight": 85,
    "cost": 10000,
    "description": "HW. Typically mounted",
    "range": 96,
    "armor_piercing": 3,
    "fire_rate": 4,
    "ammo": "Special"
  },
  {
    "name": "Pistol, Heavy",
    "damage": "2d6+1",
    "weight": 4,
    "cost": 400,
    "description": "SA",
    "range": 48,
    "armor_piercing": 4,
    "fire_rate": 1,
    "ammo": "Special"
  },
  {
    "name": "Pistol, Light",
    "damage": "2d6-1",
    "weight": 0,
    "cost": 200,
    "description": "Semi-Auto, -2 Notice to detect",
    "range": 40,
    "armor_piercing": 2,
    "fire_rate": 1,
    "ammo": "Special"
  },
  {
    "name": "Pistol, Medium",
    "damage": "2d6",
    "weight": 2,
    "cost": 300,
    "description": "SA",
    "range": 48,
    "armor_piercing": 3,
    "fire_rate": 1,
    "ammo": "Special"
  },
  {
    "name": "Plasma Pistol",
    "damage": "2d10+2",
    "weight": 7,
    "cost": 600,
    "description": "HW",
    "range": 48,
    "armor_piercing": 0,
    "fire_rate": 1,
    "ammo": "Special"
  },
  {
    "name": "Plasma Rifle",
    "damage": "3d10",
    "weight": 12,
    "cost": 1200,
    "description": "HW",
    "range": 96,
    "armor_piercing": 0,
    "fire_rate": 1,
    "ammo": "Special"
  },
  {
    "name": "Portable Missile Launcher",
    "damage": "6d6",
    "weight": 8,
    "cost": 700,
    "description": "HW, SBT, Snapfire. Missiles costs $10K and weigh 3 lb.",
    "range": 200,
    "armor_piercing": 20,
    "fire_rate": 1,
    "ammo": "Special"
  },
  {
    "name": "Shotgun",
    "damage": "1-3d6",
    "weight": 6,
    "cost": 600,
    "description": "SA",
    "range": 48,
    "armor_piercing": 0,
    "fire_rate": 1,
    "ammo": "Special"
  },
  {
    "name": "Shotgun, Full-Auto",
    "damage": "1-3d6",
    "weight": 18,
    "cost": 900,
    "description": "Notes",
    "range": 48,
    "armor_piercing": 0,
    "fire_rate": 3,
    "ammo": "Special"
  },
  {
    "name": "Sniper Rifle",
    "damage": "2d10",
    "weight": 8,
    "cost": 700,
    "description": "HW. Snapfire",
    "range": 200,
    "armor_piercing": 4,
    "fire_rate": 1,
    "ammo": "Special"
  },
  {
    "name": "Stun Gun",
    "damage": "-",
    "weight": 1,
    "cost": 300,
    "description": "On hit, Vigor roll or fall prone/incapacitated. Vigor roll each turn to revive. Success=revived but shaken. Raise=not shaken.",
    "range": 20,
    "armor_piercing": 0,
    "fire_rate": 1,
    "ammo": "Special"
  },
  {
    "name": "Submachine Gun",
    "damage": "2d6",
    "weight": 7,
    "cost": 700,
    "description": "SA, 3RB. Ammo costs $25 and weighs 2 pounds per box of 50.",
    "range": 48,
    "armor_piercing": 2,
    "fire_rate": 3,
    "ammo": "Special"
  }
]